odoo/addons/stock_picking_auto_print/README.rst
odoo/addons/stock_picking_auto_print/__init__.py
odoo/addons/stock_picking_auto_print/__manifest__.py
odoo/addons/stock_picking_auto_print/i18n/stock_picking_auto_print.pot
odoo/addons/stock_picking_auto_print/models/__init__.py
odoo/addons/stock_picking_auto_print/models/ir_actions_report.py
odoo/addons/stock_picking_auto_print/models/stock_picking.py
odoo/addons/stock_picking_auto_print/readme/CONFIGURE.rst
odoo/addons/stock_picking_auto_print/readme/CONTRIBUTORS.rst
odoo/addons/stock_picking_auto_print/readme/CREDITS.rst
odoo/addons/stock_picking_auto_print/readme/DESCRIPTION.rst
odoo/addons/stock_picking_auto_print/readme/ROADMAP.rst
odoo/addons/stock_picking_auto_print/readme/USAGE.rst
odoo/addons/stock_picking_auto_print/static/description/icon.png
odoo/addons/stock_picking_auto_print/static/description/index.html
odoo/addons/stock_picking_auto_print/tests/__init__.py
odoo/addons/stock_picking_auto_print/tests/test_stock_picking_auto_print.py
odoo/addons/stock_picking_auto_print/views/ir_action_report_view.xml
odoo13_addon_stock_picking_auto_print-13.0.1.0.1.dev5.dist-info/METADATA
odoo13_addon_stock_picking_auto_print-13.0.1.0.1.dev5.dist-info/WHEEL
odoo13_addon_stock_picking_auto_print-13.0.1.0.1.dev5.dist-info/top_level.txt
odoo13_addon_stock_picking_auto_print-13.0.1.0.1.dev5.dist-info/RECORD
